buildamol/__init__.py
buildamol/base_classes.py
buildamol/core/Linkage.py
buildamol/core/Molecule.py
buildamol/core/__init__.py
buildamol/core/entity.py
buildamol/core/reaction.py
buildamol/extensions/__init__.py
buildamol/extensions/bio/__init__.py
buildamol/extensions/bio/glycans/__init__.py
buildamol/extensions/bio/glycans/glycan.py
buildamol/extensions/bio/glycans/iupac.py
buildamol/extensions/bio/lipids/__init__.py
buildamol/extensions/bio/lipids/simple_lipids.py
buildamol/extensions/bio/nucleic_acids/__init__.py
buildamol/extensions/bio/nucleic_acids/simple_sequences.py
buildamol/extensions/bio/proteins/__init__.py
buildamol/extensions/bio/proteins/database_integrations.py
buildamol/extensions/bio/proteins/peptides.py
buildamol/extensions/bio/proteins/secondary_structure.py
buildamol/extensions/bio/proteins/utils.py
buildamol/extensions/complexes/__init__.py
buildamol/extensions/complexes/metal_complexer.py
buildamol/extensions/complexes/rotaxane_builder.py
buildamol/extensions/docking/__init__.py
buildamol/extensions/docking/dockstring.py
buildamol/extensions/docking/easydock.py
buildamol/extensions/molecular_dynamics/__init__.py
buildamol/extensions/molecular_dynamics/psf.py
buildamol/extensions/molecular_dynamics/atom_typing/__init__.py
buildamol/extensions/molecular_dynamics/atom_typing/atom_typer.py
buildamol/extensions/molecular_dynamics/atom_typing/charmm_typer.py
buildamol/extensions/molecular_dynamics/solvate/__init__.py
buildamol/extensions/molecular_dynamics/solvate/backend_biobb.py
buildamol/extensions/molecular_dynamics/solvate/backend_pdbfixer.py
buildamol/extensions/molecular_factories/__init__.py
buildamol/extensions/molecular_factories/assembler.py
buildamol/extensions/molecular_factories/derivator.py
buildamol/extensions/polymers/__init__.py
buildamol/extensions/polymers/nanotubes.py
buildamol/extensions/polymers/polycarbons.py
buildamol/graphs/__init__.py
buildamol/graphs/atom_graph.py
buildamol/graphs/base_graph.py
buildamol-1.2.11.dist-info/licenses/LICENSE.md
buildamol-1.2.11.dist-info/METADATA
buildamol-1.2.11.dist-info/WHEEL
buildamol-1.2.11.dist-info/top_level.txt
buildamol-1.2.11.dist-info/RECORD
