Metadata-Version: 2.4
Name: buildamol
Version: 1.2.11
Summary: A fragment-based molecular assembly toolkit for python.
Home-page: https://github.com/NoahHenrikKleinschmidt/buildamol
Author: Noah H. Kleinschmidt
Author-email: noah.kleinschmidt@unibe.ch
Classifier: Programming Language :: Python :: 3
Classifier: License :: OSI Approved :: GNU General Public License v3 (GPLv3)
Classifier: Operating System :: OS Independent
Classifier: Topic :: Scientific/Engineering :: Bio-Informatics
Classifier: Topic :: Scientific/Engineering :: Chemistry
Requires-Python: >=3.8
License-File: LICENSE.md
Requires-Dist: numpy
Requires-Dist: pandas
Requires-Dist: scipy
Requires-Dist: matplotlib
Requires-Dist: seaborn
Requires-Dist: networkx
Requires-Dist: biopython
Requires-Dist: pdbecif
Requires-Dist: periodictable
Requires-Dist: plotly
Requires-Dist: gym
Requires-Dist: pubchempy
Requires-Dist: tabulate
Requires-Dist: scikit-learn
Requires-Dist: ipywidgets
Requires-Dist: attrs
Requires-Dist: Deprecated
Dynamic: author
Dynamic: author-email
Dynamic: classifier
Dynamic: description
Dynamic: description-content-type
Dynamic: home-page
Dynamic: license-file
Dynamic: requires-dist
Dynamic: requires-python
Dynamic: summary
